[
  {
    "id": "1f5b1a9ca090d610",
    "username": "test",
    "password": "test",
    "expiresAt": "2026-01-31",
    "allowOffline": true
  },
  {
    "id": "061330ce9f8fce70",
    "username": "user01",
    "password": "user01",
    "expiresAt": "2026-01-04",
    "allowOffline": false
  },
  {
    "id": "dbcced6cf7ca8ace",
    "username": "mods2",
    "password": "mods2",
    "expiresAt": "2025-12-28",
    "allowOffline": true
  },
  {
    "id": "1a2174c850a58f45",
    "username": "killme",
    "password": "killme",
    "expiresAt": "2025-12-30",
    "allowOffline": true
  }
]
